ccsds_ndm/__init__.py
ccsds_ndm/ndm_io.py
ccsds_ndm/ndm_kvn_io.py
ccsds_ndm/ndm_xml_io.py
ccsds_ndm/models/__init__.py
ccsds_ndm/models/ndmxml2/__init__.py
ccsds_ndm/models/ndmxml2/ndmxml_2_0_0_aem_1_0.py
ccsds_ndm/models/ndmxml2/ndmxml_2_0_0_apm_1_0.py
ccsds_ndm/models/ndmxml2/ndmxml_2_0_0_cdm_1_0.py
ccsds_ndm/models/ndmxml2/ndmxml_2_0_0_common_2_0.py
ccsds_ndm/models/ndmxml2/ndmxml_2_0_0_master_2_0.py
ccsds_ndm/models/ndmxml2/ndmxml_2_0_0_ndm_2_0.py
ccsds_ndm/models/ndmxml2/ndmxml_2_0_0_oem_2_0.py
ccsds_ndm/models/ndmxml2/ndmxml_2_0_0_omm_2_0.py
ccsds_ndm/models/ndmxml2/ndmxml_2_0_0_opm_2_0.py
ccsds_ndm/models/ndmxml2/ndmxml_2_0_0_rdm_1_0.py
ccsds_ndm/models/ndmxml2/ndmxml_2_0_0_tdm_2_0.py
ccsds_ndm/tests/__init__.py
ccsds_ndm/tests/test_ndm_io.py
ccsds_ndm/tests/test_ndm_kvn_io.py
ccsds_ndm/tests/test_ndm_xml_io.py
ccsds_ndm/tests/data/json/omm1_ct.json
ccsds_ndm/tests/data/json/omm1_ct.xml
ccsds_ndm/tests/data/json/omm1_st.json
ccsds_ndm/tests/data/json/omm1_st.xml
ccsds_ndm/tests/data/kvn/502x0b2c1e2_fig3_2_opm.kvn
ccsds_ndm/tests/data/kvn/502x0b2c1e2_fig3_2_opm.xml
ccsds_ndm/tests/data/kvn/502x0b2c1e2_fig3_4_opm.kvn
ccsds_ndm/tests/data/kvn/502x0b2c1e2_fig3_4_opm.xml
ccsds_ndm/tests/data/kvn/504x0b1c1_fig3_6_apm.kvn
ccsds_ndm/tests/data/kvn/504x0b1c1_fig3_6_apm.xml
ccsds_ndm/tests/data/kvn/504x0b1c1_fig3_8_apm.kvn
ccsds_ndm/tests/data/kvn/504x0b1c1_fig3_8_apm.xml
ccsds_ndm/tests/data/kvn/508x1b1_figc_2_rdm.kvn
ccsds_ndm/tests/data/kvn/508x1b1_figc_2_rdm.xml
ccsds_ndm/tests/data/kvn/adm-testcase04a_abbrev.kvn
ccsds_ndm/tests/data/kvn/adm-testcase04a_abbrev.xml
ccsds_ndm/tests/data/kvn/adm-testcase04a_multi.kvn
ccsds_ndm/tests/data/kvn/adm-testcase04a_multi.xml
ccsds_ndm/tests/data/kvn/cdm_example_section4.kvn
ccsds_ndm/tests/data/kvn/cdm_example_section4.xml
ccsds_ndm/tests/data/kvn/odmv2-testcase6_abbrev.kvn
ccsds_ndm/tests/data/kvn/odmv2-testcase6_abbrev.xml
ccsds_ndm/tests/data/kvn/odmv2-testcase7a_xxx.kvn
ccsds_ndm/tests/data/kvn/odmv2-testcase7a_xxx.xml
ccsds_ndm-2.2.dist-info/LICENSE
ccsds_ndm-2.2.dist-info/WHEEL
ccsds_ndm-2.2.dist-info/METADATA
ccsds_ndm-2.2.dist-info/RECORD
