Metadata-Version: 2.1
Name: ccsds_ndm
Version: 2.2
Summary: CCSDS-NDM
Home-page: https://github.com/egemenimre/ccsds-ndm/
Keywords: satellite,satellite design,mission analysis,aerospace,engineering,astrodynamics,orbits,orbital mechanics
Author: Egemen Imre
Classifier: Intended Audience :: Science/Research
Classifier: License :: OSI Approved :: GNU General Public License v3 or later (GPLv3+)
Classifier: Operating System :: OS Independent
Classifier: Programming Language :: Python
Classifier: Programming Language :: Python :: 3
Classifier: Topic :: Scientific/Engineering
Classifier: Topic :: Scientific/Engineering :: Physics
Requires-Dist: xsdata >=20.12
Requires-Dist: sphinx ; extra == "doc"
Requires-Dist: pytest ; extra == "test"
Requires-Dist: pytest-cov ; extra == "test"
Requires-Dist: pytest-xdist ; extra == "test"
Project-URL: Documentation, https://ccsds-ndm.readthedocs.io
Provides-Extra: doc
Provides-Extra: test
